.codacy.yml
LICENSE
MANIFEST.in
README.rst
environment.yml
pyproject.toml
setup.py
/Users/mikaelmortensen/MySoftware/shenfun/shenfun/legendre/fastgl/fastgl.cpp
/Users/mikaelmortensen/MySoftware/shenfun/shenfun/legendre/fastgl/fastgl_wrap.pyx
/Users/mikaelmortensen/MySoftware/shenfun/shenfun/optimization/cython/Cheb.pyx
/Users/mikaelmortensen/MySoftware/shenfun/shenfun/optimization/cython/Matvec.pyx
/Users/mikaelmortensen/MySoftware/shenfun/shenfun/optimization/cython/applymask.pyx
/Users/mikaelmortensen/MySoftware/shenfun/shenfun/optimization/cython/convolve.pyx
/Users/mikaelmortensen/MySoftware/shenfun/shenfun/optimization/cython/cross.pyx
/Users/mikaelmortensen/MySoftware/shenfun/shenfun/optimization/cython/evaluate.pyx
/Users/mikaelmortensen/MySoftware/shenfun/shenfun/optimization/cython/la.pyx
/Users/mikaelmortensen/MySoftware/shenfun/shenfun/optimization/cython/leg2chebm.pyx
/Users/mikaelmortensen/MySoftware/shenfun/shenfun/optimization/cython/outer.pyx
/Users/mikaelmortensen/MySoftware/shenfun/shenfun/optimization/cython/transforms.pxd
/Users/mikaelmortensen/MySoftware/shenfun/shenfun/optimization/cython/transforms.pyx
shenfun/__init__.py
shenfun/config.py
shenfun/coordinates.py
shenfun/la.py
shenfun/matrixbase.py
shenfun/spectralbase.py
shenfun/tensorproductspace.py
shenfun.egg-info/PKG-INFO
shenfun.egg-info/SOURCES.txt
shenfun.egg-info/dependency_links.txt
shenfun.egg-info/requires.txt
shenfun.egg-info/top_level.txt
shenfun/chebyshev/__init__.py
shenfun/chebyshev/bases.py
shenfun/chebyshev/la.py
shenfun/chebyshev/matrices.py
shenfun/chebyshevu/__init__.py
shenfun/chebyshevu/bases.py
shenfun/chebyshevu/matrices.py
shenfun/forms/__init__.py
shenfun/forms/arguments.py
shenfun/forms/inner.py
shenfun/forms/operators.py
shenfun/forms/project.py
shenfun/fourier/__init__.py
shenfun/fourier/bases.py
shenfun/fourier/matrices.py
shenfun/hermite/__init__.py
shenfun/hermite/bases.py
shenfun/hermite/matrices.py
shenfun/io/__init__.py
shenfun/io/generate_xdmf.py
shenfun/jacobi/__init__.py
shenfun/jacobi/bases.py
shenfun/jacobi/matrices.py
shenfun/jacobi/recursions.py
shenfun/laguerre/__init__.py
shenfun/laguerre/bases.py
