Metadata-Version: 2.1
Name: shenfun
Version: 4.2.1
Summary: Shenfun -- Automated Spectral-Galerkin framework
Home-page: https://github.com/spectralDNS/shenfun
Author: Mikael Mortensen
Author-email: mikaem@math.uio.no
Classifier: Development Status :: 4 - Beta
Classifier: Environment :: Console
Classifier: Intended Audience :: Developers
Classifier: Intended Audience :: Science/Research
Classifier: Intended Audience :: Education
Classifier: Programming Language :: Python
Classifier: Programming Language :: Python :: 3
Classifier: Programming Language :: Cython
Classifier: License :: OSI Approved :: BSD License
Classifier: Topic :: Scientific/Engineering :: Mathematics
Classifier: Topic :: Software Development :: Libraries :: Python Modules
License-File: LICENSE
Requires-Dist: mpi4py-fft
Requires-Dist: mpi4py
Requires-Dist: cython
Requires-Dist: numpy
Requires-Dist: scipy
